env_replace.py
env_replace-1.1.0.dist-info/entry_points.txt
env_replace-1.1.0.dist-info/LICENSE
env_replace-1.1.0.dist-info/WHEEL
env_replace-1.1.0.dist-info/METADATA
env_replace-1.1.0.dist-info/RECORD
