Metadata-Version: 2.1
Name: env_replace
Version: 1.1.0
Summary: env-replace: un-expand environment variables for more compact output
Home-page: https://github.com/minrk/env_replace
License: UNKNOWN
Author: Min RK
Author-email: benjaminrk@gmail.com
Requires-Python: >=3
Classifier: Intended Audience :: Developers
Classifier: License :: OSI Approved :: MIT License
Classifier: Programming Language :: Python :: 3
